__init__.py
mcp_veo3.py
mcp_veo3-1.0.1.dist-info/METADATA
mcp_veo3-1.0.1.dist-info/WHEEL
mcp_veo3-1.0.1.dist-info/entry_points.txt
mcp_veo3-1.0.1.dist-info/licenses/LICENSE
mcp_veo3-1.0.1.dist-info/RECORD
