Metadata-Version: 2.4
Name: mcp-veo3
Version: 1.0.1
Summary: MCP Veo 3 Video Generator - A Model Context Protocol server for Veo 3 video generation
Project-URL: Homepage, https://github.com/dayongd1/mcp-veo3
Project-URL: Repository, https://github.com/dayongd1/mcp-veo3
Project-URL: Documentation, https://github.com/dayongd1/mcp-veo3/blob/main/README.md
Project-URL: Bug Tracker, https://github.com/dayongd1/mcp-veo3/issues
Project-URL: Changelog, https://github.com/dayongd1/mcp-veo3/releases
Author-email: Dayong Huang <dayong.d1@gmail.com>
Maintainer-email: Dayong Huang <dayong.d1@gmail.com>
License: MIT
License-File: LICENSE
Keywords: ai,fastmcp,gemini,generation,google,mcp,model-context-protocol,veo,video
Classifier: Development Status :: 4 - Beta
Classifier: Intended Audience :: Developers
Classifier: License :: OSI Approved :: MIT License
Classifier: Operating System :: OS Independent
Classifier: Programming Language :: Python :: 3
Classifier: Programming Language :: Python :: 3.10
Classifier: Programming Language :: Python :: 3.11
Classifier: Programming Language :: Python :: 3.12
Classifier: Topic :: Internet :: WWW/HTTP :: HTTP Servers
Classifier: Topic :: Multimedia :: Video
Classifier: Topic :: Scientific/Engineering :: Artificial Intelligence
Classifier: Topic :: Software Development :: Libraries :: Python Modules
Requires-Python: >=3.10
Requires-Dist: fastmcp>=2.11.0
Requires-Dist: google-genai>=0.3.0
Requires-Dist: pillow>=10.0.0
Requires-Dist: pydantic>=2.11.0
Requires-Dist: python-dotenv>=1.1.0
